tilemani/__init__.py
tilemani/compute/__init__.py
tilemani/compute/features.py
tilemani-0.0.1.dist-info/LICENSE
tilemani-0.0.1.dist-info/METADATA
tilemani-0.0.1.dist-info/WHEEL
tilemani-0.0.1.dist-info/top_level.txt
tilemani-0.0.1.dist-info/RECORD
