Metadata-Version: 2.1
Name: tilemani
Version: 0.0.1
Summary: A collection of tools to retreive OSM data, rasterize them into customizable style, compute geospatial features and build models of urban space
Home-page: https://github.com/cocoaaa/TileMani
Author: Hayley Song
Author-email: haejinso@usc.edu
License: UNKNOWN
Platform: UNKNOWN
Requires-Python: >=3.6
License-File: LICENSE
